zhaostephen/rebrn/__init__.py
zhaostephen/rebrn/__main__.py
zhaostephen/rebrn/py.typed
zhaostephen/rebrn/_internal/__init__.py
zhaostephen/rebrn/_internal/exceptions.py
zhaostephen/rebrn/_internal/table_printer.py
zhaostephen/rebrn/_internal/cli/__init__.py
zhaostephen/rebrn/_internal/cli/main.py
zhaostephen/rebrn/_internal/cli/main_parser.py
zhaostephen_rebrn-0.1.2.dist-info/LICENSE
zhaostephen_rebrn-0.1.2.dist-info/METADATA
zhaostephen_rebrn-0.1.2.dist-info/WHEEL
zhaostephen_rebrn-0.1.2.dist-info/entry_points.txt
zhaostephen_rebrn-0.1.2.dist-info/top_level.txt
zhaostephen_rebrn-0.1.2.dist-info/RECORD
